[
  {
    "Artist": "Gabriel Iglesias: Don't Worry Be Fluffy (TMUSA)",
    "agentCodes": "(TMUSA)",
    "link": "https://www.ticketmaster.com/event/1100608443405DA9",
    "venue": "Rogers Arena",
    "city": "Vancouver, BC",
    "Eventdate": "Sat, 9/21/2024 8:00 PM",
    "presaleDate": "4/11/2024 12:30 AM",
    "publicDate": "4/12/2024 12:30 AM"
  },
  {
    "Artist": "Gabriel Iglesias: Don't Worry Be Fluffy (TMUSA)",
    "agentCodes": "(TMUSA)",
    "link": "https://www.ticketmaster.com/event/11006083A65A3772",
    "venue": "SaskTel Centre",
    "city": "Saskatoon, SK",
    "Eventdate": "Fri, 9/27/2024 8:00 PM",
    "presaleDate": "4/11/2024 12:30 AM",
    "publicDate": "4/12/2024 12:30 AM"
  },
  {
    "Artist": "Gabriel Iglesias: Don't Worry Be Fluffy (TMUSA)",
    "agentCodes": "(TMUSA)",
    "link": "https://www.ticketmaster.com/event/19006083AED73F5E",
    "venue": "Findlay Toyota Center",
    "city": "Prescott Valley, AZ",
    "Eventdate": "Sun, 10/6/2024 7:30 PM",
    "presaleDate": "4/11/2024 12:30 AM",
    "publicDate": "4/12/2024 12:30 AM"
  },
  {
    "Artist": "Gabriel Iglesias: Don't Worry Be Fluffy (TMUSA)",
    "agentCodes": "(TMUSA)",
    "link": "https://www.ticketmaster.com/event/00006083A2AE2B2A",
    "venue": "The Event Center at Turning Stone Resort Casino",
    "city": "Verona, NY",
    "Eventdate": "Sat, 7/6/2024 8:00 PM",
    "presaleDate": "4/11/2024 7:30 PM",
    "publicDate": "4/12/2024 7:30 PM"
  },
  {
    "Artist": "Gabriel Iglesias: Don't Worry Be Fluffy (TMUSA)",
    "agentCodes": "(TMUSA)",
    "link": "https://www.ticketmaster.com/event/2200607BAB301BA2",
    "venue": "Donald L. Tucker Civic Center",
    "city": "Tallahassee, FL",
    "Eventdate": "Fri, 11/8/2024 8:00 PM",
    "presaleDate": "4/9/2024 9:30 PM",
    "publicDate": "4/11/2024 9:30 PM"
  },
  {
    "Artist": "Gabriel Iglesias: Don't Worry Be Fluffy (TMUSA)",
    "agentCodes": "(TMUSA)",
    "link": "https://www.ticketmaster.com/event/0D006085E5074662",
    "venue": "Amalie Arena",
    "city": "Tampa, FL",
    "Eventdate": "Sat, 11/9/2024 8:00 PM",
    "presaleDate": "4/10/2024 9:30 PM",
    "publicDate": "4/11/2024 9:30 PM"
  },
  {
    "Artist": "Gabriel Iglesias: Don't Worry Be Fluffy (TMUSA)",
    "agentCodes": "(TMUSA)",
    "link": "https://www.ticketmaster.com/event/0D00607CA3DC2584",
    "venue": "Hertz Arena",
    "city": "Estero, FL",
    "Eventdate": "Sun, 11/10/2024 7:30 PM",
    "presaleDate": "4/10/2024 9:30 PM",
    "publicDate": "4/11/2024 9:30 PM"
  },
  {
    "Artist": "Gabriel Iglesias: Don't Worry Be Fluffy (TMUSA)",
    "agentCodes": "(TMUSA)",
    "link": "https://www.ticketmaster.com/event/1B0060839BAF3D89",
    "venue": "Soldiers and Sailors Memorial Auditorium",
    "city": "Chattanooga, TN",
    "Eventdate": "Fri, 11/29/2024 8:00 PM",
    "presaleDate": "4/10/2024 9:30 PM",
    "publicDate": "4/11/2024 9:30 PM"
  },
  {
    "Artist": "Gabriel Iglesias: Don't Worry Be Fluffy (TMUSA)",
    "agentCodes": "(TMUSA)",
    "link": "https://www.ticketmaster.com/event/0E006081AF6E301A",
    "venue": "Macon Coliseum",
    "city": "Macon, GA",
    "Eventdate": "Sat, 11/30/2024 8:00 PM",
    "presaleDate": "4/10/2024 9:30 PM",
    "publicDate": "4/11/2024 9:30 PM"
  },
  {
    "Artist": "Gabriel Iglesias: Don't Worry Be Fluffy (TMUSA)",
    "agentCodes": "(TMUSA)",
    "link": "https://www.ticketmaster.com/event/11006085F85F56FF",
    "venue": "Canada Life Centre",
    "city": "Winnipeg, MB",
    "Eventdate": "Sat, 9/28/2024 8:00 PM",
    "presaleDate": "4/9/2024 10:30 PM",
    "publicDate": "4/11/2024 10:30 PM"
  },
  {
    "Artist": "Gabriel Iglesias: Don't Worry Be Fluffy (TMUSA)",
    "agentCodes": "(TMUSA)",
    "link": "https://www.ticketmaster.com/event/190060849C6B1D8C",
    "venue": "Tucson Arena",
    "city": "Tucson, AZ",
    "Eventdate": "Sat, 10/5/2024 8:00 PM",
    "presaleDate": "4/10/2024 10:30 PM",
    "publicDate": "4/11/2024 10:30 PM"
  },
  {
    "Artist": "Gabriel Iglesias: Don't Worry Be Fluffy (TMUSA)",
    "agentCodes": "(TMUSA)",
    "link": "https://www.ticketmaster.com/event/3A00607CE44355F4",
    "venue": "American Bank Center Arena",
    "city": "Corpus Christi, TX",
    "Eventdate": "Thu, 10/10/2024 8:00 PM",
    "presaleDate": "4/10/2024 7:30 PM",
    "publicDate": "4/11/2024 10:30 PM"
  },
  {
    "Artist": "Gabriel Iglesias: Don't Worry Be Fluffy (TMUSA)",
    "agentCodes": "(TMUSA)",
    "link": "https://www.ticketmaster.com/event/3A0060769CC138E9",
    "venue": "Moody Center ATX",
    "city": "Austin, TX",
    "Eventdate": "Fri, 10/11/2024 8:00 PM",
    "presaleDate": "4/10/2024 10:30 PM",
    "publicDate": "4/11/2024 10:30 PM"
  },
  {
    "Artist": "Gabriel Iglesias: Don't Worry Be Fluffy (TMUSA)",
    "agentCodes": "(TMUSA)",
    "link": "https://www.ticketmaster.com/event/3A00608529467EAF",
    "venue": "Ford Park",
    "city": "Beaumont, TX",
    "Eventdate": "Sat, 10/12/2024 8:00 PM",
    "presaleDate": "4/10/2024 10:30 PM",
    "publicDate": "4/11/2024 10:30 PM"
  },
  {
    "Artist": "Gabriel Iglesias: Don't Worry Be Fluffy (TMUSA)",
    "agentCodes": "(TMUSA)",
    "link": "https://www.ticketmaster.com/event/06006083916A2E37",
    "venue": "Alliant Energy PowerHouse",
    "city": "Cedar Rapids, IA",
    "Eventdate": "Fri, 10/25/2024 8:00 PM",
    "presaleDate": "4/10/2024 10:30 PM",
    "publicDate": "4/11/2024 10:30 PM"
  },
  {
    "Artist": "Gabriel Iglesias: Don't Worry Be Fluffy (TMUSA)",
    "agentCodes": "(TMUSA)",
    "link": "https://www.ticketmaster.com/event/060060839A103713",
    "venue": "Cable Dahmer Arena",
    "city": "Independence, MO",
    "Eventdate": "Sat, 10/26/2024 8:00 PM",
    "presaleDate": "4/10/2024 10:30 PM",
    "publicDate": "4/11/2024 10:30 PM"
  },
  {
    "Artist": "Gabriel Iglesias: Don't Worry Be Fluffy (TMUSA)",
    "agentCodes": "(TMUSA)",
    "link": "https://www.ticketmaster.com/event/200060839B091A15",
    "venue": "Legacy Arena at The BJCC",
    "city": "Birmingham, AL",
    "Eventdate": "Sun, 12/1/2024 7:30 PM",
    "presaleDate": "4/9/2024 10:30 AM",
    "publicDate": "4/11/2024 10:30 PM"
  },
  {
    "Artist": "Gabriel Iglesias: Don't Worry Be Fluffy (EVNU)",
    "agentCodes": "(EVNU)",
    "link": "https://aac-uaa.evenue.net/cgi-bin/ncommerce3/SEGetEventInfo?ticketCode=GS:UAA:AAC24:GI0919:&linkID=global-uaa&dataAccId=341&locale=en_US&siteId=ev_global-uaa",
    "venue": "Alaska Airlines Center",
    "city": "Anchorage, AK",
    "Eventdate": "Thu, 9/19/2024 8:00 PM",
    "presaleDate": "4/9/2024 11:30 PM",
    "publicDate": "4/11/2024 11:30 PM"
  },
  {
    "Artist": "Gabriel Iglesias: Don't Worry Be Fluffy (TMUSA)",
    "agentCodes": "(TMUSA)",
    "link": "https://www.ticketmaster.com/event/11006083E3B34CE1",
    "venue": "Rogers Place",
    "city": "Edmonton, AB",
    "Eventdate": "Thu, 9/26/2024 8:00 PM",
    "presaleDate": "4/10/2024 11:30 PM",
    "publicDate": "4/11/2024 11:30 PM"
  },
  {
    "Artist": "Gabriel Iglesias: Don't Worry Be Fluffy (TMUSA)",
    "agentCodes": "(TMUSA)",
    "link": "https://www.ticketmaster.com/event/0C006083D3F64A6B",
    "venue": "Don Haskins Center",
    "city": "El Paso, TX",
    "Eventdate": "Fri, 10/4/2024 8:00 PM",
    "presaleDate": "4/10/2024 11:30 PM",
    "publicDate": "4/11/2024 11:30 PM"
  }
]